generalvector/__init__.py
generalvector/general.py
generalvector/vector.py
generalvector/vector2.py
generalvector/test/test_generalvector.py
generalvector/test/test_vector.py
generalvector/test/test_vector2.py
generalvector-1.5.114.dist-info/LICENSE
generalvector-1.5.114.dist-info/METADATA
generalvector-1.5.114.dist-info/WHEEL
generalvector-1.5.114.dist-info/top_level.txt
generalvector-1.5.114.dist-info/RECORD
