Metadata-Version: 2.1
Name: generalvector
Version: 1.5.114
Summary: Simple immutable vectors.
Home-page: https://github.com/ManderaGeneral/generalvector
Author: Rickard "Mandera" Abraham
Author-email: rickard.abraham@gmail.com
License: mit
Classifier: Topic :: Utilities
Classifier: Programming Language :: Python :: 3.8
Classifier: Programming Language :: Python :: 3.9
Classifier: Programming Language :: Python :: 3.10
Classifier: Programming Language :: Python :: 3.11
Classifier: License :: OSI Approved :: MIT License
Classifier: Operating System :: Microsoft :: Windows
Classifier: Operating System :: POSIX :: Linux
License-File: LICENSE
Requires-Dist: generallibrary
